[
  {
    "timestamp": "1539447051",
    "user": "admin",
    "message": "31123312"
  },
  {
    "timestamp": "1539447053",
    "user": "admin",
    "message": "dsada"
  },
  {
    "timestamp": "1539447056",
    "user": "admin",
    "message": "csa  "
  },
  {
    "timestamp": "1539447076",
    "user": "tolian",
    "message": "   312312"
  },
  {
    "timestamp": "1539447078",
    "user": "tolian",
    "message": "31312"
  },
  {
    "timestamp": "1539465904",
    "user": "admin",
    "message": "4124132"
  },
  {
    "timestamp": "1539466002",
    "user": "admin",
    "message": "414314"
  },
  {
    "timestamp": "1539466004",
    "user": "admin",
    "message": "4124312"
  },
  {
    "timestamp": "1539466017",
    "user": "qwerty",
    "message": "312312"
  },
  {
    "timestamp": "1539522631",
    "user": "admin1",
    "message": "31312"
  },
  {
    "timestamp": "1539522649",
    "user": "admintolian",
    "message": "31232"
  },
  {
    "timestamp": "1539524150",
    "user": "\u0442\u0435\u0441\u04421",
    "message": "1"
  },
  {
    "timestamp": "1539524159",
    "user": "admin",
    "message": "312"
  },
  {
    "timestamp": "1540454095",
    "user": "admin1",
    "message": "75467"
  },
  {
    "timestamp": "1540455636",
    "user": "admin1",
    "message": "432214"
  },
  {
    "timestamp": "1540455638",
    "user": "admin1",
    "message": "431243124"
  },
  {
    "timestamp": "1540455639",
    "user": "admin1",
    "message": "rewqrweq"
  },
  {
    "timestamp": "1540459473",
    "user": "admin1",
    "message": "312312"
  },
  {
    "timestamp": "1540470033",
    "user": "admin",
    "message": "4532"
  },
  {
    "timestamp": "1540632675",
    "user": "admin",
    "message": "96789"
  },
  {
    "timestamp": "1540653887",
    "user": "admin",
    "message": "3213123"
  },
  {
    "timestamp": "1540667828",
    "user": "admin",
    "message": "4234"
  },
  {
    "timestamp": "1540667829",
    "user": "admin",
    "message": "53452"
  },
  {
    "timestamp": "1540836458",
    "user": "admin",
    "message": "74574467"
  },
  {
    "timestamp": "1540838497",
    "user": "admin",
    "message": "465745"
  },
  {
    "timestamp": "1540846002",
    "user": "admin",
    "message": "dhfghffdh :) dasdas"
  },
  {
    "timestamp": "1540846010",
    "user": "admin",
    "message": "855856"
  },
  {
    "timestamp": "1540846012",
    "user": "admin",
    "message": "rutruruy"
  },
  {
    "timestamp": "1540846015",
    "user": "admin",
    "message": "turtumr  tyu ruy "
  },
  {
    "timestamp": "1540846021",
    "user": "admin",
    "message": "hs ga:) fsd"
  },
  {
    "timestamp": "1540846028",
    "user": "admin",
    "message": "4u47u6"
  },
  {
    "timestamp": "1540846029",
    "user": "admin",
    "message": "kghm"
  },
  {
    "timestamp": "1540846039",
    "user": "admin",
    "message": "48467"
  },
  {
    "timestamp": "1540846063",
    "user": "admin",
    "message": "657878"
  },
  {
    "timestamp": "1540846454",
    "user": "admin",
    "message": "45745"
  },
  {
    "timestamp": "1540846459",
    "user": "admin",
    "message": "478487"
  },
  {
    "timestamp": "1540846484",
    "user": "admin",
    "message": "477"
  },
  {
    "timestamp": "1540846525",
    "user": "admin",
    "message": "2\u04512\u0451"
  },
  {
    "timestamp": "1540846533",
    "user": "admin",
    "message": "\u044b\u0439\u0446\u0439\u0432\u0446\u0443\u0432\u0439\u0446\u0432\u0439\u0446\u0432"
  },
  {
    "timestamp": "1540846610",
    "user": "admin",
    "message": "12342134"
  },
  {
    "timestamp": "1540846618",
    "user": "admin",
    "message": "3`123`123"
  },
  {
    "timestamp": "1540846623",
    "user": "admin",
    "message": "r43dsc xz"
  },
  {
    "timestamp": "1540846647",
    "user": "admin",
    "message": "31321312"
  },
  {
    "timestamp": "1540846734",
    "user": "admin",
    "message": "31`312"
  },
  {
    "timestamp": "1540846740",
    "user": "admin",
    "message": "23414132"
  },
  {
    "timestamp": "1540846743",
    "user": "admin",
    "message": "4131432"
  },
  {
    "timestamp": "1540846766",
    "user": "admin",
    "message": "41241243"
  },
  {
    "timestamp": "1540846920",
    "user": "admin",
    "message": "12334124314324312"
  },
  {
    "timestamp": "1540846924",
    "user": "admin",
    "message": "3`2`13`2312313212341243"
  },
  {
    "timestamp": "1540846927",
    "user": "admin",
    "message": "2e1wqwssxsdxc"
  },
  {
    "timestamp": "1540846948",
    "user": "admin",
    "message": "14324213"
  },
  {
    "timestamp": "1540846977",
    "user": "admin",
    "message": "41234231433412"
  },
  {
    "timestamp": "1540847019",
    "user": "admin",
    "message": "31412356"
  },
  {
    "timestamp": "1540881794",
    "user": "admin",
    "message": "768"
  },
  {
    "timestamp": "1540883566",
    "user": "admin",
    "message": "312321"
  },
  {
    "timestamp": "1540883689",
    "user": "admin",
    "message": "312312"
  },
  {
    "timestamp": "1540883691",
    "user": "admin",
    "message": "31222321"
  },
  {
    "timestamp": "1540883691",
    "user": "admin",
    "message": ""
  },
  {
    "timestamp": "1540931597",
    "user": "admin",
    "message": "6345"
  },
  {
    "timestamp": "1540931618",
    "user": "admin",
    "message": "654"
  },
  {
    "timestamp": "1540931632",
    "user": "test2",
    "message": "364654"
  },
  {
    "timestamp": "1540936185",
    "user": "test2",
    "message": "48"
  },
  {
    "timestamp": "1540936294",
    "user": "test2",
    "message": "47"
  }
]